{
    "dataset": "Hepta",
    "kmeans_centroids": [
        {
            "centroid": 0,
            "values": {
                "X1": -2.9951883999999995,
                "X2": -0.013736333333333364,
                "X3": 0.0882396
            },
            "prediction": "[0.6432415  0.05573175 0.         0.         0.30102673 0.\n 0.        ]",
            "class": "0",
            "rules": [
                {
                    "rule": "X1 < -1.093",
                    "mass_class_1": 0.43455469608306885,
                    "mass_class_2": 0.0,
                    "mass_class_3": 0.0,
                    "mass_class_4": 0.0,
                    "mass_class_5": 0.0,
                    "mass_class_6": 0.0,
                    "mass_class_7": 0.0,
                    "uncertainty": 0.5654453039169312
                },
                {
                    "rule": "-1.090 < X2 < 0.034",
                    "mass_class_1": 0.2467222362756729,
                    "mass_class_2": 0.09616545587778091,
                    "mass_class_3": 0.0,
                    "mass_class_4": 0.20837253332138062,
                    "mass_class_5": 0.23084379732608795,
                    "mass_class_6": 0.21789595484733582,
                    "mass_class_7": 0.0,
                    "uncertainty": 0.0
                },
                {
                    "rule": "-0.036 < X3 < 1.060",
                    "mass_class_1": 0.24222718179225922,
                    "mass_class_2": 0.09522480517625809,
                    "mass_class_3": 0.25060775876045227,
                    "mass_class_4": 0.0,
                    "mass_class_5": 0.21426604688167572,
                    "mass_class_6": 0.0,
                    "mass_class_7": 0.19767418503761292,
                    "uncertainty": 0.0
                }
            ]
        },
        {
            "centroid": 1,
            "values": {
                "X1": -0.004240718750000009,
                "X2": 0.004758156250000003,
                "X3": 0.007246718750000006
            },
            "prediction": "[0. 1. 0. 0. 0. 0. 0.]",
            "class": "1",
            "rules": [
                {
                    "rule": "-1.093 < X1 < 0.015",
                    "mass_class_1": 0.0,
                    "mass_class_2": 0.10592221468687057,
                    "mass_class_3": 0.20444242656230927,
                    "mass_class_4": 0.21933531761169434,
                    "mass_class_5": 0.0,
                    "mass_class_6": 0.20987112820148468,
                    "mass_class_7": 0.26042887568473816,
                    "uncertainty": 0.0
                },
                {
                    "rule": "-1.090 < X2 < 0.034",
                    "mass_class_1": 0.2467222362756729,
                    "mass_class_2": 0.09616545587778091,
                    "mass_class_3": 0.0,
                    "mass_class_4": 0.20837253332138062,
                    "mass_class_5": 0.23084379732608795,
                    "mass_class_6": 0.21789595484733582,
                    "mass_class_7": 0.0,
                    "uncertainty": 0.0
                },
                {
                    "rule": "-0.036 < X3 < 1.060",
                    "mass_class_1": 0.24222718179225922,
                    "mass_class_2": 0.09522480517625809,
                    "mass_class_3": 0.25060775876045227,
                    "mass_class_4": 0.0,
                    "mass_class_5": 0.21426604688167572,
                    "mass_class_6": 0.0,
                    "mass_class_7": 0.19767418503761292,
                    "uncertainty": 0.0
                }
            ]
        },
        {
            "centroid": 2,
            "values": {
                "X1": 0.13998693333333334,
                "X2": 3.081746966666667,
                "X3": 0.07450500000000002
            },
            "prediction": "[0.         0.00236873 0.73290336 0.         0.         0.\n 0.2647279 ]",
            "class": "2",
            "rules": [
                {
                    "rule": "X2 > 1.158",
                    "mass_class_1": 0.0,
                    "mass_class_2": 0.0,
                    "mass_class_3": 0.4213833808898926,
                    "mass_class_4": 0.0,
                    "mass_class_5": 0.0,
                    "mass_class_6": 0.0,
                    "mass_class_7": 0.0,
                    "uncertainty": 0.5786166191101074
                },
                {
                    "rule": "0.015 < X1 < 1.124",
                    "mass_class_1": 0.0,
                    "mass_class_2": 0.004233127925544977,
                    "mass_class_3": 0.2879639267921448,
                    "mass_class_4": 0.2335798293352127,
                    "mass_class_5": 0.0,
                    "mass_class_6": 0.24632282555103302,
                    "mass_class_7": 0.22790022194385529,
                    "uncertainty": 0.0
                },
                {
                    "rule": "-0.036 < X3 < 1.060",
                    "mass_class_1": 0.24222718179225922,
                    "mass_class_2": 0.09522480517625809,
                    "mass_class_3": 0.25060775876045227,
                    "mass_class_4": 0.0,
                    "mass_class_5": 0.21426604688167572,
                    "mass_class_6": 0.0,
                    "mass_class_7": 0.19767418503761292,
                    "uncertainty": 0.0
                }
            ]
        },
        {
            "centroid": 3,
            "values": {
                "X1": -0.047262166666666654,
                "X2": 0.045800633333333333,
                "X3": -3.0427618999999995
            },
            "prediction": "[0.         0.04122987 0.         0.6205515  0.         0.33821863\n 0.        ]",
            "class": "3",
            "rules": [
                {
                    "rule": "X3 < -1.132",
                    "mass_class_1": 0.0,
                    "mass_class_2": 0.0,
                    "mass_class_3": 0.0,
                    "mass_class_4": 0.4371893107891083,
                    "mass_class_5": 0.0,
                    "mass_class_6": 0.0,
                    "mass_class_7": 0.0,
                    "uncertainty": 0.5628106594085693
                },
                {
                    "rule": "0.034 < X2 < 1.158",
                    "mass_class_1": 0.2343887835741043,
                    "mass_class_2": 0.05441358685493469,
                    "mass_class_3": 0.0,
                    "mass_class_4": 0.2225942611694336,
                    "mass_class_5": 0.2633209526538849,
                    "mass_class_6": 0.22528237104415894,
                    "mass_class_7": 0.0,
                    "uncertainty": 0.0
                },
                {
                    "rule": "-1.093 < X1 < 0.015",
                    "mass_class_1": 0.0,
                    "mass_class_2": 0.10592221468687057,
                    "mass_class_3": 0.20444242656230927,
                    "mass_class_4": 0.21933531761169434,
                    "mass_class_5": 0.0,
                    "mass_class_6": 0.20987112820148468,
                    "mass_class_7": 0.26042887568473816,
                    "uncertainty": 0.0
                }
            ]
        },
        {
            "centroid": 4,
            "values": {
                "X1": 2.9995383000000007,
                "X2": -0.0011308666666666814,
                "X3": -0.1400596
            },
            "prediction": "[0.3354821  0.03433169 0.         0.         0.6301862  0.\n 0.        ]",
            "class": "4",
            "rules": [
                {
                    "rule": "X1 > 1.124",
                    "mass_class_1": 0.0,
                    "mass_class_2": 0.0,
                    "mass_class_3": 0.0,
                    "mass_class_4": 0.0,
                    "mass_class_5": 0.4267406463623047,
                    "mass_class_6": 0.0,
                    "mass_class_7": 0.0,
                    "uncertainty": 0.5732593536376953
                },
                {
                    "rule": "-1.132 < X3 < -0.036",
                    "mass_class_1": 0.22287340462207794,
                    "mass_class_2": 0.05851582810282707,
                    "mass_class_3": 0.19895026087760925,
                    "mass_class_4": 0.0,
                    "mass_class_5": 0.25650689005851746,
                    "mass_class_6": 0.0,
                    "mass_class_7": 0.2631535828113556,
                    "uncertainty": 0.0
                },
                {
                    "rule": "-1.090 < X2 < 0.034",
                    "mass_class_1": 0.2467222362756729,
                    "mass_class_2": 0.09616545587778091,
                    "mass_class_3": 0.0,
                    "mass_class_4": 0.20837253332138062,
                    "mass_class_5": 0.23084379732608795,
                    "mass_class_6": 0.21789595484733582,
                    "mass_class_7": 0.0,
                    "uncertainty": 0.0
                }
            ]
        },
        {
            "centroid": 5,
            "values": {
                "X1": -0.006311899999999997,
                "X2": 0.09194213333333331,
                "X3": 2.8723619999999985
            },
            "prediction": "[0.         0.04238139 0.         0.3590074  0.         0.59861124\n 0.        ]",
            "class": "5",
            "rules": [
                {
                    "rule": "X3 > 1.060",
                    "mass_class_1": 0.0,
                    "mass_class_2": 0.0,
                    "mass_class_3": 0.0,
                    "mass_class_4": 0.0,
                    "mass_class_5": 0.0,
                    "mass_class_6": 0.41921430826187134,
                    "mass_class_7": 0.0,
                    "uncertainty": 0.5807856917381287
                },
                {
                    "rule": "0.034 < X2 < 1.158",
                    "mass_class_1": 0.2343887835741043,
                    "mass_class_2": 0.05441358685493469,
                    "mass_class_3": 0.0,
                    "mass_class_4": 0.2225942611694336,
                    "mass_class_5": 0.2633209526538849,
                    "mass_class_6": 0.22528237104415894,
                    "mass_class_7": 0.0,
                    "uncertainty": 0.0
                },
                {
                    "rule": "-1.093 < X1 < 0.015",
                    "mass_class_1": 0.0,
                    "mass_class_2": 0.10592221468687057,
                    "mass_class_3": 0.20444242656230927,
                    "mass_class_4": 0.21933531761169434,
                    "mass_class_5": 0.0,
                    "mass_class_6": 0.20987112820148468,
                    "mass_class_7": 0.26042887568473816,
                    "uncertainty": 0.0
                }
            ]
        },
        {
            "centroid": 6,
            "values": {
                "X1": 0.022712300000000008,
                "X2": -2.968135966666667,
                "X3": -0.11177456666666663
            },
            "prediction": "[0.         0.00153716 0.35552323 0.         0.         0.\n 0.6429396 ]",
            "class": "6",
            "rules": [
                {
                    "rule": "X2 < -1.090",
                    "mass_class_1": 0.0,
                    "mass_class_2": 0.0,
                    "mass_class_3": 0.0,
                    "mass_class_4": 0.0,
                    "mass_class_5": 0.0,
                    "mass_class_6": 0.0,
                    "mass_class_7": 0.4211457669734955,
                    "uncertainty": 0.5788542032241821
                },
                {
                    "rule": "-1.132 < X3 < -0.036",
                    "mass_class_1": 0.22287340462207794,
                    "mass_class_2": 0.05851582810282707,
                    "mass_class_3": 0.19895026087760925,
                    "mass_class_4": 0.0,
                    "mass_class_5": 0.25650689005851746,
                    "mass_class_6": 0.0,
                    "mass_class_7": 0.2631535828113556,
                    "uncertainty": 0.0
                },
                {
                    "rule": "0.015 < X1 < 1.124",
                    "mass_class_1": 0.0,
                    "mass_class_2": 0.004233127925544977,
                    "mass_class_3": 0.2879639267921448,
                    "mass_class_4": 0.2335798293352127,
                    "mass_class_5": 0.0,
                    "mass_class_6": 0.24632282555103302,
                    "mass_class_7": 0.22790022194385529,
                    "uncertainty": 0.0
                }
            ]
        }
    ],
    "dsc_rules": {
        "0": [
            [
                "0.24672224",
                5,
                "-1.090 < X2 < 0.034",
                "0.49671143",
                "[0.24672224 0.09616546 0.         0.20837253 0.2308438  0.21789595\n 0.         0.        ]"
            ],
            [
                "0.24222718",
                10,
                "-0.036 < X3 < 1.060",
                "0.4921658",
                "[0.24222718 0.09522481 0.25060776 0.         0.21426605 0.\n 0.19767419 0.        ]"
            ],
            [
                "0.23438878",
                6,
                "0.034 < X2 < 1.158",
                "0.48413715",
                "[0.23438878 0.05441359 0.         0.22259426 0.26332095 0.22528237\n 0.         0.        ]"
            ],
            [
                "0.2228734",
                9,
                "-1.132 < X3 < -0.036",
                "0.47209468",
                "[0.2228734  0.05851583 0.19895026 0.         0.2565069  0.\n 0.26315358 0.        ]"
            ],
            [
                "0.18883778",
                0,
                "X1 < -1.093",
                "0.4345547",
                "[0.4345547 0.        0.        0.        0.        0.        0.\n 0.5654453]"
            ]
        ],
        "1": [
            [
                "0.105922215",
                1,
                "-1.093 < X1 < 0.015",
                "0.32545692",
                "[0.         0.10592221 0.20444243 0.21933532 0.         0.20987113\n 0.26042888 0.        ]"
            ],
            [
                "0.096165456",
                5,
                "-1.090 < X2 < 0.034",
                "0.31010556",
                "[0.24672224 0.09616546 0.         0.20837253 0.2308438  0.21789595\n 0.         0.        ]"
            ],
            [
                "0.095224805",
                10,
                "-0.036 < X3 < 1.060",
                "0.30858517",
                "[0.24222718 0.09522481 0.25060776 0.         0.21426605 0.\n 0.19767419 0.        ]"
            ],
            [
                "0.058515828",
                9,
                "-1.132 < X3 < -0.036",
                "0.24190044",
                "[0.2228734  0.05851583 0.19895026 0.         0.2565069  0.\n 0.26315358 0.        ]"
            ],
            [
                "0.054413587",
                6,
                "0.034 < X2 < 1.158",
                "0.2332672",
                "[0.23438878 0.05441359 0.         0.22259426 0.26332095 0.22528237\n 0.         0.        ]"
            ],
            [
                "0.004233128",
                2,
                "0.015 < X1 < 1.124",
                "0.06506249",
                "[0.         0.00423313 0.28796393 0.23357983 0.         0.24632283\n 0.22790022 0.        ]"
            ]
        ],
        "2": [
            [
                "0.28796393",
                2,
                "0.015 < X1 < 1.124",
                "0.5366227",
                "[0.         0.00423313 0.28796393 0.23357983 0.         0.24632283\n 0.22790022 0.        ]"
            ],
            [
                "0.25060776",
                10,
                "-0.036 < X3 < 1.060",
                "0.5006074",
                "[0.24222718 0.09522481 0.25060776 0.         0.21426605 0.\n 0.19767419 0.        ]"
            ],
            [
                "0.20444243",
                1,
                "-1.093 < X1 < 0.015",
                "0.4521531",
                "[0.         0.10592221 0.20444243 0.21933532 0.         0.20987113\n 0.26042888 0.        ]"
            ],
            [
                "0.19895026",
                9,
                "-1.132 < X3 < -0.036",
                "0.4460384",
                "[0.2228734  0.05851583 0.19895026 0.         0.2565069  0.\n 0.26315358 0.        ]"
            ],
            [
                "0.17756395",
                7,
                "X2 > 1.158",
                "0.42138338",
                "[0.         0.         0.42138338 0.         0.         0.\n 0.         0.5786166 ]"
            ]
        ],
        "3": [
            [
                "0.23357983",
                2,
                "0.015 < X1 < 1.124",
                "0.48330098",
                "[0.         0.00423313 0.28796393 0.23357983 0.         0.24632283\n 0.22790022 0.        ]"
            ],
            [
                "0.22259426",
                6,
                "0.034 < X2 < 1.158",
                "0.47179896",
                "[0.23438878 0.05441359 0.         0.22259426 0.26332095 0.22528237\n 0.         0.        ]"
            ],
            [
                "0.21933532",
                1,
                "-1.093 < X1 < 0.015",
                "0.4683325",
                "[0.         0.10592221 0.20444243 0.21933532 0.         0.20987113\n 0.26042888 0.        ]"
            ],
            [
                "0.20837253",
                5,
                "-1.090 < X2 < 0.034",
                "0.45647842",
                "[0.24672224 0.09616546 0.         0.20837253 0.2308438  0.21789595\n 0.         0.        ]"
            ],
            [
                "0.19113451",
                8,
                "X3 < -1.132",
                "0.43718934",
                "[0.         0.         0.         0.4371893  0.         0.\n 0.         0.56281066]"
            ]
        ],
        "4": [
            [
                "0.26332095",
                6,
                "0.034 < X2 < 1.158",
                "0.51314807",
                "[0.23438878 0.05441359 0.         0.22259426 0.26332095 0.22528237\n 0.         0.        ]"
            ],
            [
                "0.2565069",
                9,
                "-1.132 < X3 < -0.036",
                "0.5064651",
                "[0.2228734  0.05851583 0.19895026 0.         0.2565069  0.\n 0.26315358 0.        ]"
            ],
            [
                "0.2308438",
                5,
                "-1.090 < X2 < 0.034",
                "0.48046207",
                "[0.24672224 0.09616546 0.         0.20837253 0.2308438  0.21789595\n 0.         0.        ]"
            ],
            [
                "0.21426605",
                10,
                "-0.036 < X3 < 1.060",
                "0.4628888",
                "[0.24222718 0.09522481 0.25060776 0.         0.21426605 0.\n 0.19767419 0.        ]"
            ],
            [
                "0.18210758",
                3,
                "X1 > 1.124",
                "0.42674065",
                "[0.         0.         0.         0.         0.42674065 0.\n 0.         0.57325935]"
            ]
        ],
        "5": [
            [
                "0.24632283",
                2,
                "0.015 < X1 < 1.124",
                "0.4963092",
                "[0.         0.00423313 0.28796393 0.23357983 0.         0.24632283\n 0.22790022 0.        ]"
            ],
            [
                "0.22528237",
                6,
                "0.034 < X2 < 1.158",
                "0.4746392",
                "[0.23438878 0.05441359 0.         0.22259426 0.26332095 0.22528237\n 0.         0.        ]"
            ],
            [
                "0.21789595",
                5,
                "-1.090 < X2 < 0.034",
                "0.46679327",
                "[0.24672224 0.09616546 0.         0.20837253 0.2308438  0.21789595\n 0.         0.        ]"
            ],
            [
                "0.20987113",
                1,
                "-1.093 < X1 < 0.015",
                "0.45811695",
                "[0.         0.10592221 0.20444243 0.21933532 0.         0.20987113\n 0.26042888 0.        ]"
            ],
            [
                "0.17574063",
                11,
                "X3 > 1.060",
                "0.4192143",
                "[0.        0.        0.        0.        0.        0.4192143 0.\n 0.5807857]"
            ]
        ],
        "6": [
            [
                "0.26315358",
                9,
                "-1.132 < X3 < -0.036",
                "0.512985",
                "[0.2228734  0.05851583 0.19895026 0.         0.2565069  0.\n 0.26315358 0.        ]"
            ],
            [
                "0.26042888",
                1,
                "-1.093 < X1 < 0.015",
                "0.51032233",
                "[0.         0.10592221 0.20444243 0.21933532 0.         0.20987113\n 0.26042888 0.        ]"
            ],
            [
                "0.22790022",
                2,
                "0.015 < X1 < 1.124",
                "0.47738895",
                "[0.         0.00423313 0.28796393 0.23357983 0.         0.24632283\n 0.22790022 0.        ]"
            ],
            [
                "0.19767419",
                10,
                "-0.036 < X3 < 1.060",
                "0.44460565",
                "[0.24222718 0.09522481 0.25060776 0.         0.21426605 0.\n 0.19767419 0.        ]"
            ],
            [
                "0.17736377",
                4,
                "X2 < -1.090",
                "0.42114577",
                "[0.         0.         0.         0.         0.         0.\n 0.42114577 0.5788542 ]"
            ]
        ]
    }
}