{
    "dataset": "Target",
    "kmeans_centroids": [
        {
            "centroid": 0,
            "values": {
                "X1": -1.1703187228915661,
                "X2": -1.2657697108433734
            },
            "prediction": "[0.9683918  0.         0.         0.03160823 0.         0.        ]",
            "class": "0",
            "rules": [
                {
                    "rule": "X2 < -0.634",
                    "mass_class_1": 0.36002612113952637,
                    "mass_class_2": 0.0,
                    "mass_class_3": 0.0,
                    "mass_class_4": 0.0,
                    "mass_class_5": 0.6339384317398071,
                    "mass_class_6": 0.0,
                    "uncertainty": 0.006035447120666504
                },
                {
                    "rule": "X1 < -0.632",
                    "mass_class_1": 0.3356070816516876,
                    "mass_class_2": 0.0,
                    "mass_class_3": 0.0,
                    "mass_class_4": 0.6643928289413452,
                    "mass_class_5": 0.0,
                    "mass_class_6": 0.0,
                    "uncertainty": 0.0
                }
            ]
        },
        {
            "centroid": 1,
            "values": {
                "X1": 1.6623969875000004,
                "X2": 0.4137655750000001
            },
            "prediction": "[0.         0.9897088  0.         0.         0.00672001 0.00357118]",
            "class": "1",
            "rules": [
                {
                    "rule": "X1 > 0.664",
                    "mass_class_1": 0.0,
                    "mass_class_2": 0.7867336273193359,
                    "mass_class_3": 0.0,
                    "mass_class_4": 0.0,
                    "mass_class_5": 0.13926008343696594,
                    "mass_class_6": 0.07400635629892349,
                    "uncertainty": 0.0
                },
                {
                    "rule": "0.007 < X2 < 0.647",
                    "mass_class_1": 0.0,
                    "mass_class_2": 0.162703737616539,
                    "mass_class_3": 0.6985722184181213,
                    "mass_class_4": 0.13223402202129364,
                    "mass_class_5": 0.0,
                    "mass_class_6": 0.0,
                    "uncertainty": 0.0064900461584329605
                }
            ]
        },
        {
            "centroid": 2,
            "values": {
                "X1": 0.009090891139240501,
                "X2": -0.023263022784810128
            },
            "prediction": "[0.04857725 0.00594921 0.93001837 0.00129503 0.00129503 0.01286515]",
            "class": "2",
            "rules": [
                {
                    "rule": "-0.634 < X2 < 0.007",
                    "mass_class_1": 0.10427219420671463,
                    "mass_class_2": 0.14911456406116486,
                    "mass_class_3": 0.7051219940185547,
                    "mass_class_4": 0.0,
                    "mass_class_5": 0.0,
                    "mass_class_6": 0.0,
                    "uncertainty": 0.04149120673537254
                },
                {
                    "rule": "-0.632 < X1 < 0.016",
                    "mass_class_1": 0.1653652787208557,
                    "mass_class_2": 0.0,
                    "mass_class_3": 0.6648783683776855,
                    "mass_class_4": 0.0,
                    "mass_class_5": 0.0,
                    "mass_class_6": 0.15266837179660797,
                    "uncertainty": 0.01708795689046383
                }
            ]
        },
        {
            "centroid": 3,
            "values": {
                "X1": -1.4727462051282052,
                "X2": 0.9965236794871792
            },
            "prediction": "[0.11327455 0.         0.         0.8867254  0.         0.        ]",
            "class": "3",
            "rules": [
                {
                    "rule": "X1 < -0.632",
                    "mass_class_1": 0.3356070816516876,
                    "mass_class_2": 0.0,
                    "mass_class_3": 0.0,
                    "mass_class_4": 0.6643928289413452,
                    "mass_class_5": 0.0,
                    "mass_class_6": 0.0,
                    "uncertainty": 0.0
                },
                {
                    "rule": "X2 > 0.647",
                    "mass_class_1": 0.0,
                    "mass_class_2": 0.057512007653713226,
                    "mass_class_3": 0.0,
                    "mass_class_4": 0.10594682395458221,
                    "mass_class_5": 0.0,
                    "mass_class_6": 0.800678551197052,
                    "uncertainty": 0.03586263582110405
                }
            ]
        },
        {
            "centroid": 4,
            "values": {
                "X1": 1.0030903333333332,
                "X2": -1.439466463768116
            },
            "prediction": "[0.         0.05034352 0.         0.         0.9449207  0.00473571]",
            "class": "4",
            "rules": [
                {
                    "rule": "X2 < -0.634",
                    "mass_class_1": 0.36002612113952637,
                    "mass_class_2": 0.0,
                    "mass_class_3": 0.0,
                    "mass_class_4": 0.0,
                    "mass_class_5": 0.6339384317398071,
                    "mass_class_6": 0.0,
                    "uncertainty": 0.006035447120666504
                },
                {
                    "rule": "X1 > 0.664",
                    "mass_class_1": 0.0,
                    "mass_class_2": 0.7867336273193359,
                    "mass_class_3": 0.0,
                    "mass_class_4": 0.0,
                    "mass_class_5": 0.13926008343696594,
                    "mass_class_6": 0.07400635629892349,
                    "uncertainty": 0.0
                }
            ]
        },
        {
            "centroid": 5,
            "values": {
                "X1": 0.27988519999999995,
                "X2": 1.6584788769230772
            },
            "prediction": "[0.00844841 0.02199691 0.15664002 0.03340703 0.04653097 0.7329766 ]",
            "class": "5",
            "rules": [
                {
                    "rule": "X2 > 0.647",
                    "mass_class_1": 0.0,
                    "mass_class_2": 0.057512007653713226,
                    "mass_class_3": 0.0,
                    "mass_class_4": 0.10594682395458221,
                    "mass_class_5": 0.0,
                    "mass_class_6": 0.800678551197052,
                    "uncertainty": 0.03586263582110405
                },
                {
                    "rule": "0.016 < X1 < 0.664",
                    "mass_class_1": 0.0,
                    "mass_class_2": 0.0,
                    "mass_class_3": 0.6807242035865784,
                    "mass_class_4": 0.0,
                    "mass_class_5": 0.17493382096290588,
                    "mass_class_6": 0.10553385317325592,
                    "uncertainty": 0.038808103650808334
                }
            ]
        }
    ],
    "dsc_rules": {
        "0": [
            [
                "0.3578532",
                4,
                "X2 < -0.634",
                "0.5982083",
                "[0.36002612 0.         0.         0.         0.63393843 0.\n 0.00603545]"
            ],
            [
                "0.33560708",
                0,
                "X1 < -0.632",
                "0.579316",
                "[0.33560708 0.         0.         0.6643928  0.         0.\n 0.        ]"
            ],
            [
                "0.16253953",
                1,
                "-0.632 < X1 < 0.016",
                "0.4031619",
                "[0.16536528 0.         0.66487837 0.         0.         0.15266837\n 0.01708796]"
            ],
            [
                "0.09994581",
                5,
                "-0.634 < X2 < 0.007",
                "0.31614208",
                "[0.10427219 0.14911456 0.705122   0.         0.         0.\n 0.04149121]"
            ]
        ],
        "1": [
            [
                "0.7867336",
                3,
                "X1 > 0.664",
                "0.88698006",
                "[0.         0.7867336  0.         0.         0.13926008 0.07400636\n 0.        ]"
            ],
            [
                "0.16164778",
                6,
                "0.007 < X2 < 0.647",
                "0.40205446",
                "[0.         0.16270374 0.6985722  0.13223402 0.         0.\n 0.00649005]"
            ],
            [
                "0.14292762",
                5,
                "-0.634 < X2 < 0.007",
                "0.3780577",
                "[0.10427219 0.14911456 0.705122   0.         0.         0.\n 0.04149121]"
            ],
            [
                "0.055449475",
                7,
                "X2 > 0.647",
                "0.23547712",
                "[0.         0.05751201 0.         0.10594682 0.         0.80067855\n 0.03586264]"
            ]
        ],
        "2": [
            [
                "0.69403845",
                6,
                "0.007 < X2 < 0.647",
                "0.8330897",
                "[0.         0.16270374 0.6985722  0.13223402 0.         0.\n 0.00649005]"
            ],
            [
                "0.67586565",
                5,
                "-0.634 < X2 < 0.007",
                "0.8221105",
                "[0.10427219 0.14911456 0.705122   0.         0.         0.\n 0.04149121]"
            ],
            [
                "0.6543066",
                2,
                "0.016 < X1 < 0.664",
                "0.8088922",
                "[0.         0.         0.6807242  0.         0.17493382 0.10553385\n 0.0388081 ]"
            ],
            [
                "0.65351695",
                1,
                "-0.632 < X1 < 0.016",
                "0.80840397",
                "[0.16536528 0.         0.66487837 0.         0.         0.15266837\n 0.01708796]"
            ]
        ],
        "3": [
            [
                "0.6643928",
                0,
                "X1 < -0.632",
                "0.81510293",
                "[0.33560708 0.         0.         0.6643928  0.         0.\n 0.        ]"
            ],
            [
                "0.13137582",
                6,
                "0.007 < X2 < 0.647",
                "0.36245802",
                "[0.         0.16270374 0.6985722  0.13223402 0.         0.\n 0.00649005]"
            ],
            [
                "0.102147296",
                7,
                "X2 > 0.647",
                "0.3196049",
                "[0.         0.05751201 0.         0.10594682 0.         0.80067855\n 0.03586264]"
            ]
        ],
        "4": [
            [
                "0.63011235",
                4,
                "X2 < -0.634",
                "0.7937962",
                "[0.36002612 0.         0.         0.         0.63393843 0.\n 0.00603545]"
            ],
            [
                "0.16814497",
                2,
                "0.016 < X1 < 0.664",
                "0.41005483",
                "[0.         0.         0.6807242  0.         0.17493382 0.10553385\n 0.0388081 ]"
            ],
            [
                "0.13926008",
                3,
                "X1 > 0.664",
                "0.37317568",
                "[0.         0.7867336  0.         0.         0.13926008 0.07400636\n 0.        ]"
            ]
        ],
        "5": [
            [
                "0.77196413",
                7,
                "X2 > 0.647",
                "0.8786149",
                "[0.         0.05751201 0.         0.10594682 0.         0.80067855\n 0.03586264]"
            ],
            [
                "0.15005958",
                1,
                "-0.632 < X1 < 0.016",
                "0.38737524",
                "[0.16536528 0.         0.66487837 0.         0.         0.15266837\n 0.01708796]"
            ],
            [
                "0.101438284",
                2,
                "0.016 < X1 < 0.664",
                "0.31849378",
                "[0.         0.         0.6807242  0.         0.17493382 0.10553385\n 0.0388081 ]"
            ],
            [
                "0.07400636",
                3,
                "X1 > 0.664",
                "0.27204108",
                "[0.         0.7867336  0.         0.         0.13926008 0.07400636\n 0.        ]"
            ]
        ]
    }
}